ego/__init__.py
ego/appl.py
ego/run_test.py
ego/scenario_setting.json
ego/data/__init__.py
ego/data/investment_costs.csv
ego/data/investment_costs_of_grid_ measures.csv
ego/examples/__init__.py
ego/examples/tutorials/README.md
ego/examples/tutorials/edisgo_simple_example.ipynb
ego/examples/tutorials/etrago_OpenMod_Zuerich18.ipynb
ego/examples/tutorials/grid_1476.png
ego/examples/tutorials/requirements.yml
ego/tools/__init__.py
ego/tools/config.json
ego/tools/economics.py
ego/tools/edisgo_integration.py
ego/tools/io.py
ego/tools/mv_cluster.py
ego/tools/plots.py
ego/tools/results.py
ego/tools/specs.py
ego/tools/storages.py
ego/tools/utilities.py
eGo-0.3.4.dist-info/LICENSE
eGo-0.3.4.dist-info/METADATA
eGo-0.3.4.dist-info/WHEEL
eGo-0.3.4.dist-info/dependency_links.txt
eGo-0.3.4.dist-info/top_level.txt
eGo-0.3.4.dist-info/RECORD
