Metadata-Version: 2.1
Name: eGo
Version: 0.3.4
Summary: A cross-grid-level electricity grid and storage optimization tool 
Home-page: https://github.com/openego/eGo
Author: wolfbunke, maltesc
Author-email: wolf-dieter.bunke@uni-flensburg.de
License: GNU Affero General Public License Version 3 (AGPL-3.0)
Platform: UNKNOWN
Requires-Dist: egoio (==0.4.5)
Requires-Dist: ding0 (==v0.1.9)
Requires-Dist: pycallgraph
Requires-Dist: eDisGo (==v0.0.9)
Requires-Dist: eTraGo (==0.7.1)
Requires-Dist: scikit-learn (==0.19.0)
Requires-Dist: pandas (==0.20.3)
Requires-Dist: pypsa (==0.11.0fork)
Requires-Dist: sqlalchemy (==1.2.0)
Requires-Dist: geoalchemy2 (<=0.4.0,>=0.3.0)
Requires-Dist: tsam (==0.9.9)
Requires-Dist: geopandas
Requires-Dist: matplotlib (==3.0.0)
Requires-Dist: Rtree
Requires-Dist: descartes
Requires-Dist: pyproj
Requires-Dist: plotly (==2.2.3)
Requires-Dist: shapely
Requires-Dist: multiprocess
Requires-Dist: folium
Requires-Dist: oedialect
Provides-Extra: doc
Requires-Dist: sphinx (>=1.4) ; extra == 'doc'
Requires-Dist: sphinx-rtd-theme ; extra == 'doc'
Requires-Dist: sphinxcontrib-httpdomain ; extra == 'doc'
Requires-Dist: numpydoc (==0.7.0) ; extra == 'doc'
Requires-Dist: aiohttp-jinja2 ; extra == 'doc'
Requires-Dist: sphinx-jsondomain ; extra == 'doc'
